.hgignore
.hgtags
ABOUT.txt
CHANGES.txt
COPYRIGHT.txt
LICENSE.txt
README.txt
buildout.cfg
setup.py
doc/about.txt
doc/api.txt
doc/conf.py
doc/narrative.txt
doc/static/custom.css
doc/templates/autosummary/module.rst
tl/__init__.py
tl.testing.egg-info/PKG-INFO
tl.testing.egg-info/SOURCES.txt
tl.testing.egg-info/dependency_links.txt
tl.testing.egg-info/namespace_packages.txt
tl.testing.egg-info/not-zip-safe
tl.testing.egg-info/requires.txt
tl.testing.egg-info/top_level.txt
tl/testing/__init__.py
tl/testing/cairo-technical.txt
tl/testing/cairo.py
tl/testing/cairo.txt
tl/testing/doctest.py
tl/testing/fs.py
tl/testing/fs.txt
tl/testing/script.py
tl/testing/script.txt
tl/testing/thread.py
tl/testing/thread.txt
tl/testing/testimages/correct.png
tl/testing/testimages/red-line-bug.png
tl/testing/testimages/red-line.png
tl/testing/testimages/rgb24.png
tl/testing/testimages/vertical.png
tl/testing/tests/__init__.py
tl/testing/tests/test_doctests.py