Metadata-Version: 1.0
Name: tl.testing
Version: 0.5
Summary: Utilities for writing tests: sandbox directories, mock external programs,
Home-page: http://packages.python.org/tl.testing/
Author: Thomas Lotze
Author-email: thomas@thomas-lotze.de
License: ZPL 2.1
Keywords: testing unittest doctest file directory tree sandbox helper ls mkdir mock script manuel cairo graphics image
Platform: UNKNOWN
Classifier: Development Status :: 3 - Alpha
Classifier: Intended Audience :: Developers
Classifier: License :: OSI Approved :: Zope Public License
Classifier: Programming Language :: Python
Classifier: Topic :: Software Development :: Testing
